dbt/__init__.py
dbt/adapters/__init__.py
dbt/adapters/postgres/__init__.py
dbt/adapters/postgres/__version__.py
dbt/adapters/postgres/column.py
dbt/adapters/postgres/connections.py
dbt/adapters/postgres/impl.py
dbt/adapters/postgres/relation.py
dbt/adapters/postgres/relation_configs/__init__.py
dbt/adapters/postgres/relation_configs/constants.py
dbt/adapters/postgres/relation_configs/index.py
dbt/adapters/postgres/relation_configs/materialized_view.py
dbt/include/postgres/__init__.py
dbt/include/postgres/dbt_project.yml
dbt/include/postgres/profile_template.yml
dbt/include/postgres/sample_profiles.yml
dbt/include/postgres/macros/adapters.sql
dbt/include/postgres/macros/catalog.sql
dbt/include/postgres/macros/relations.sql
dbt/include/postgres/macros/timestamps.sql
dbt/include/postgres/macros/materializations/incremental_strategies.sql
dbt/include/postgres/macros/materializations/snapshot_merge.sql
dbt/include/postgres/macros/relations/materialized_view/alter.sql
dbt/include/postgres/macros/relations/materialized_view/create.sql
dbt/include/postgres/macros/relations/materialized_view/describe.sql
dbt/include/postgres/macros/relations/materialized_view/drop.sql
dbt/include/postgres/macros/relations/materialized_view/refresh.sql
dbt/include/postgres/macros/relations/materialized_view/rename.sql
dbt/include/postgres/macros/relations/table/drop.sql
dbt/include/postgres/macros/relations/table/rename.sql
dbt/include/postgres/macros/relations/table/replace.sql
dbt/include/postgres/macros/relations/view/drop.sql
dbt/include/postgres/macros/relations/view/rename.sql
dbt/include/postgres/macros/relations/view/replace.sql
dbt/include/postgres/macros/utils/any_value.sql
dbt/include/postgres/macros/utils/columns_spec_ddl.sql
dbt/include/postgres/macros/utils/dateadd.sql
dbt/include/postgres/macros/utils/datediff.sql
dbt/include/postgres/macros/utils/last_day.sql
dbt/include/postgres/macros/utils/listagg.sql
dbt/include/postgres/macros/utils/split_part.sql
dbt_postgres-1.7.19.dist-info/METADATA
dbt_postgres-1.7.19.dist-info/WHEEL
dbt_postgres-1.7.19.dist-info/top_level.txt
dbt_postgres-1.7.19.dist-info/RECORD
