Metadata-Version: 2.1
Name: dbt-postgres
Version: 1.7.19
Summary: The postgres adapter plugin for dbt (data build tool)
Home-page: https://github.com/dbt-labs/dbt-core
Author: dbt Labs
Author-email: info@dbtlabs.com
Classifier: Development Status :: 5 - Production/Stable
Classifier: License :: OSI Approved :: Apache Software License
Classifier: Operating System :: Microsoft :: Windows
Classifier: Operating System :: MacOS :: MacOS X
Classifier: Operating System :: POSIX :: Linux
Classifier: Programming Language :: Python :: 3.8
Classifier: Programming Language :: Python :: 3.9
Classifier: Programming Language :: Python :: 3.10
Classifier: Programming Language :: Python :: 3.11
Requires-Python: >=3.8
Requires-Dist: dbt-core==1.7.19
Requires-Dist: psycopg2-binary~=2.8
Requires-Dist: agate
